{
  "metadata": {
    "time_window_met": "at_service_end",
    "cost_components": {
      "travel_time": 1,
      "total_tardiness": 1,
      "highest_tardiness": 2,
      "total_waiting_time": 8,
      "total_extra_time": 4,
      "max_idle_time": 27,
      "caregiver_preferences": 9,
      "optional_patients": 180,
      "missed_lunch_break": 90
    },
    "name": "mixed-generated-v12/instance-Saragoza-r_60-p_50-dp_1-apt_same_as_departure-h600-twm_at_service_end-rs_42-inc_0-opt_0-dtw_0.5-pcgr_0-sc_(3, 3)-sp_1.0",
    "origin": "generated",
    "horizon": 600,
    "generator_info": {
      "city": "Saragoza",
      "radius": 60.0,
      "patients": 50,
      "departing_points": 1,
      "arrival_points": 0,
      "arrival_point_type": "same_as_departure",
      "sync_rates": [
        1.0,
        0.0,
        0.0,
        0.0
      ],
      "incompatibility": 0.0,
      "service_classes": [
        3,
        3
      ],
      "optional_rate": 0.0,
      "double_time_window_rate": 0.5,
      "preferred_caregiver_rate": 0.0,
      "no_intersect_administrative": false,
      "patient_config": {
        "time_windows": [
          120
        ],
        "treatment_durations": [
          15,
          35
        ],
        "treatment_duration_biases": [
          0.5,
          0.5
        ],
        "sequential_distances": [
          0
        ],
        "time_window_granularity": 15
      },
      "caregiver_config": {
        "shift_durations": [
          600
        ],
        "shift_granularity": 30
      },
      "random_seed": 42
    }
  },
  "distances": [
    [
      0,
      41,
      7,
      6,
      15,
      16,
      15,
      7,
      51,
      46,
      14,
      5,
      10,
      7,
      7,
      14,
      9,
      13,
      7,
      5,
      10,
      9,
      7,
      18,
      13,
      17,
      27,
      46,
      10,
      18,
      6,
      13,
      10,
      25,
      27,
      13,
      8,
      5,
      19,
      44,
      29,
      10,
      54,
      51,
      26,
      33,
      5,
      3,
      7,
      26,
      12
    ],
    [
      43,
      0,
      40,
      41,
      43,
      45,
      31,
      40,
      66,
      18,
      34,
      42,
      41,
      38,
      38,
      40,
      38,
      38,
      42,
      40,
      37,
      38,
      41,
      57,
      42,
      46,
      54,
      12,
      39,
      48,
      37,
      43,
      38,
      60,
      22,
      42,
      37,
      41,
      30,
      17,
      56,
      36,
      27,
      65,
      48,
      67,
      43,
      42,
      44,
      23,
      40
    ],
    [
      7,
      39,
      0,
      4,
      10,
      17,
      13,
      3,
      51,
      44,
      15,
      9,
      12,
      9,
      8,
      15,
      11,
      14,
      11,
      7,
      11,
      6,
      11,
      21,
      15,
      18,
      22,
      44,
      5,
      13,
      5,
      14,
      11,
      27,
      25,
      15,
      7,
      5,
      17,
      42,
      24,
      7,
      52,
      50,
      25,
      35,
      9,
      4,
      11,
      24,
      14
    ],
    [
      7,
      41,
      4,
      0,
      12,
      19,
      15,
      5,
      53,
      46,
      15,
      9,
      12,
      9,
      9,
      16,
      11,
      14,
      11,
      7,
      11,
      8,
      11,
      21,
      16,
      20,
      24,
      46,
      7,
      15,
      6,
      15,
      12,
      28,
      26,
      16,
      7,
      6,
      18,
      44,
      27,
      9,
      54,
      52,
      26,
      36,
      9,
      4,
      10,
      26,
      15
    ],
    [
      15,
      44,
      9,
      12,
      0,
      22,
      18,
      12,
      56,
      49,
      21,
      18,
      19,
      18,
      17,
      22,
      19,
      20,
      16,
      16,
      20,
      15,
      19,
      19,
      20,
      22,
      25,
      49,
      9,
      12,
      14,
      18,
      20,
      21,
      30,
      22,
      16,
      14,
      22,
      47,
      28,
      16,
      57,
      55,
      29,
      29,
      16,
      12,
      15,
      29,
      23
    ],
    [
      23,
      53,
      25,
      26,
      28,
      0,
      27,
      27,
      35,
      58,
      24,
      24,
      18,
      20,
      23,
      25,
      20,
      24,
      20,
      22,
      21,
      28,
      21,
      31,
      17,
      11,
      40,
      57,
      24,
      31,
      25,
      15,
      23,
      38,
      38,
      19,
      25,
      26,
      29,
      57,
      42,
      26,
      67,
      45,
      30,
      45,
      24,
      23,
      21,
      37,
      20
    ],
    [
      16,
      29,
      13,
      15,
      16,
      19,
      0,
      13,
      48,
      35,
      7,
      15,
      14,
      11,
      11,
      13,
      11,
      11,
      16,
      13,
      10,
      12,
      14,
      30,
      16,
      19,
      27,
      34,
      13,
      22,
      11,
      16,
      11,
      33,
      15,
      15,
      11,
      14,
      7,
      37,
      30,
      9,
      45,
      47,
      21,
      41,
      17,
      15,
      17,
      14,
      14
    ],
    [
      7,
      39,
      4,
      5,
      12,
      20,
      12,
      0,
      50,
      43,
      14,
      9,
      12,
      9,
      7,
      14,
      10,
      13,
      11,
      7,
      10,
      5,
      11,
      23,
      14,
      20,
      23,
      43,
      7,
      16,
      4,
      15,
      10,
      30,
      24,
      14,
      6,
      6,
      16,
      41,
      25,
      6,
      51,
      49,
      24,
      37,
      9,
      6,
      12,
      23,
      13
    ],
    [
      51,
      66,
      52,
      53,
      55,
      39,
      49,
      51,
      0,
      63,
      46,
      52,
      46,
      48,
      50,
      46,
      48,
      46,
      48,
      50,
      46,
      50,
      49,
      59,
      45,
      39,
      66,
      65,
      51,
      59,
      49,
      43,
      50,
      66,
      59,
      44,
      50,
      53,
      51,
      70,
      68,
      48,
      58,
      26,
      35,
      73,
      52,
      51,
      48,
      59,
      47
    ],
    [
      46,
      19,
      44,
      45,
      47,
      49,
      35,
      43,
      64,
      0,
      38,
      45,
      44,
      42,
      42,
      44,
      42,
      41,
      46,
      44,
      41,
      42,
      45,
      60,
      46,
      50,
      58,
      11,
      43,
      52,
      41,
      46,
      41,
      64,
      26,
      46,
      41,
      45,
      35,
      17,
      60,
      40,
      19,
      63,
      52,
      71,
      47,
      46,
      48,
      27,
      44
    ],
    [
      11,
      40,
      6,
      8,
      9,
      18,
      13,
      8,
      51,
      44,
      0,
      14,
      16,
      14,
      13,
      18,
      16,
      16,
      13,
      12,
      16,
      11,
      16,
      22,
      16,
      19,
      21,
      44,
      5,
      14,
      10,
      15,
      16,
      26,
      25,
      18,
      12,
      10,
      17,
      42,
      24,
      12,
      52,
      50,
      25,
      33,
      13,
      9,
      12,
      24,
      19
    ],
    [
      6,
      41,
      9,
      9,
      18,
      16,
      15,
      9,
      51,
      46,
      14,
      0,
      7,
      5,
      5,
      14,
      6,
      12,
      4,
      4,
      9,
      10,
      3,
      20,
      11,
      16,
      29,
      46,
      13,
      21,
      8,
      10,
      8,
      27,
      26,
      12,
      8,
      7,
      18,
      44,
      31,
      10,
      54,
      52,
      27,
      35,
      6,
      7,
      5,
      26,
      11
    ],
    [
      9,
      40,
      12,
      11,
      18,
      11,
      14,
      12,
      46,
      45,
      13,
      6,
      0,
      4,
      6,
      11,
      4,
      9,
      3,
      6,
      6,
      12,
      5,
      21,
      6,
      11,
      30,
      45,
      15,
      21,
      9,
      5,
      7,
      28,
      25,
      8,
      9,
      9,
      17,
      43,
      32,
      11,
      53,
      48,
      22,
      36,
      10,
      9,
      6,
      25,
      7
    ],
    [
      6,
      38,
      8,
      8,
      17,
      13,
      12,
      8,
      48,
      43,
      11,
      4,
      4,
      0,
      3,
      10,
      3,
      9,
      4,
      2,
      6,
      8,
      3,
      20,
      8,
      13,
      27,
      43,
      11,
      20,
      6,
      7,
      5,
      27,
      24,
      9,
      6,
      6,
      16,
      41,
      29,
      8,
      51,
      49,
      24,
      35,
      6,
      6,
      6,
      23,
      8
    ],
    [
      9,
      37,
      8,
      10,
      17,
      16,
      10,
      8,
      50,
      41,
      10,
      7,
      7,
      4,
      0,
      10,
      5,
      8,
      7,
      5,
      5,
      7,
      7,
      23,
      9,
      16,
      26,
      41,
      12,
      20,
      4,
      10,
      5,
      30,
      22,
      9,
      4,
      7,
      14,
      40,
      28,
      7,
      49,
      48,
      23,
      37,
      9,
      8,
      9,
      22,
      8
    ],
    [
      16,
      37,
      17,
      18,
      20,
      17,
      12,
      16,
      45,
      43,
      11,
      14,
      10,
      10,
      10,
      0,
      9,
      6,
      12,
      12,
      6,
      15,
      12,
      28,
      11,
      17,
      31,
      42,
      16,
      25,
      13,
      12,
      10,
      35,
      23,
      7,
      12,
      16,
      14,
      42,
      33,
      12,
      52,
      44,
      19,
      43,
      16,
      16,
      15,
      22,
      7
    ],
    [
      9,
      39,
      12,
      12,
      20,
      12,
      13,
      12,
      47,
      44,
      12,
      7,
      3,
      4,
      5,
      10,
      0,
      8,
      5,
      6,
      5,
      10,
      5,
      23,
      7,
      11,
      29,
      44,
      15,
      24,
      8,
      6,
      5,
      30,
      24,
      7,
      8,
      9,
      16,
      42,
      32,
      9,
      52,
      48,
      23,
      38,
      10,
      10,
      8,
      24,
      6
    ],
    [
      13,
      35,
      13,
      14,
      18,
      16,
      10,
      12,
      46,
      41,
      9,
      11,
      8,
      7,
      8,
      6,
      7,
      0,
      10,
      10,
      4,
      11,
      10,
      28,
      9,
      16,
      28,
      40,
      14,
      23,
      8,
      11,
      7,
      34,
      20,
      8,
      7,
      12,
      12,
      40,
      31,
      9,
      50,
      45,
      20,
      42,
      13,
      13,
      13,
      20,
      7
    ],
    [
      9,
      43,
      11,
      11,
      17,
      15,
      17,
      11,
      49,
      47,
      16,
      5,
      5,
      7,
      7,
      14,
      7,
      12,
      0,
      5,
      9,
      12,
      5,
      19,
      10,
      14,
      28,
      48,
      13,
      20,
      10,
      8,
      10,
      26,
      28,
      11,
      10,
      9,
      20,
      46,
      31,
      12,
      56,
      50,
      25,
      34,
      9,
      9,
      4,
      28,
      10
    ],
    [
      4,
      39,
      6,
      6,
      15,
      16,
      13,
      6,
      50,
      44,
      12,
      5,
      6,
      3,
      3,
      12,
      5,
      10,
      6,
      0,
      7,
      8,
      6,
      19,
      10,
      15,
      27,
      44,
      10,
      18,
      6,
      9,
      7,
      26,
      25,
      10,
      6,
      4,
      17,
      42,
      29,
      8,
      52,
      50,
      25,
      33,
      4,
      4,
      7,
      24,
      9
    ],
    [
      10,
      36,
      11,
      12,
      19,
      13,
      11,
      11,
      47,
      42,
      10,
      9,
      4,
      5,
      5,
      7,
      4,
      5,
      7,
      7,
      0,
      10,
      7,
      25,
      6,
      13,
      29,
      41,
      15,
      23,
      7,
      7,
      5,
      32,
      22,
      6,
      7,
      10,
      13,
      41,
      31,
      9,
      51,
      46,
      20,
      39,
      11,
      10,
      9,
      21,
      5
    ],
    [
      9,
      38,
      7,
      8,
      15,
      20,
      11,
      6,
      49,
      42,
      12,
      10,
      10,
      7,
      6,
      13,
      8,
      11,
      11,
      8,
      9,
      0,
      11,
      25,
      13,
      19,
      23,
      42,
      10,
      18,
      3,
      13,
      9,
      31,
      23,
      13,
      5,
      7,
      15,
      40,
      26,
      3,
      50,
      48,
      23,
      39,
      11,
      8,
      13,
      23,
      12
    ],
    [
      8,
      42,
      10,
      10,
      19,
      15,
      15,
      10,
      50,
      46,
      14,
      4,
      6,
      4,
      6,
      14,
      5,
      12,
      4,
      4,
      9,
      11,
      0,
      22,
      10,
      15,
      30,
      46,
      13,
      22,
      8,
      9,
      8,
      28,
      27,
      11,
      8,
      8,
      19,
      44,
      32,
      11,
      54,
      52,
      26,
      36,
      8,
      8,
      5,
      26,
      10
    ],
    [
      18,
      54,
      19,
      20,
      20,
      29,
      27,
      22,
      64,
      58,
      29,
      20,
      24,
      22,
      21,
      30,
      23,
      28,
      21,
      20,
      25,
      24,
      22,
      0,
      27,
      29,
      35,
      58,
      19,
      26,
      22,
      25,
      25,
      12,
      39,
      28,
      23,
      21,
      31,
      56,
      37,
      25,
      66,
      64,
      39,
      20,
      18,
      17,
      20,
      39,
      27
    ],
    [
      14,
      42,
      16,
      16,
      21,
      10,
      16,
      16,
      45,
      47,
      14,
      12,
      6,
      8,
      9,
      10,
      7,
      11,
      9,
      10,
      7,
      14,
      9,
      23,
      0,
      11,
      32,
      46,
      17,
      24,
      12,
      5,
      9,
      30,
      27,
      4,
      12,
      14,
      19,
      46,
      35,
      13,
      56,
      45,
      20,
      38,
      14,
      14,
      11,
      27,
      6
    ],
    [
      17,
      46,
      18,
      20,
      22,
      4,
      21,
      20,
      39,
      52,
      18,
      15,
      10,
      12,
      14,
      18,
      12,
      17,
      12,
      14,
      14,
      20,
      13,
      25,
      11,
      0,
      34,
      51,
      18,
      25,
      18,
      8,
      15,
      32,
      32,
      13,
      18,
      18,
      23,
      51,
      36,
      19,
      61,
      49,
      24,
      39,
      17,
      17,
      14,
      31,
      13
    ],
    [
      27,
      53,
      23,
      25,
      26,
      34,
      27,
      24,
      65,
      58,
      30,
      30,
      30,
      27,
      25,
      31,
      28,
      29,
      28,
      28,
      28,
      23,
      30,
      38,
      32,
      34,
      0,
      58,
      23,
      29,
      22,
      30,
      29,
      43,
      39,
      32,
      24,
      26,
      31,
      56,
      10,
      24,
      66,
      64,
      38,
      51,
      28,
      25,
      27,
      38,
      31
    ],
    [
      46,
      12,
      44,
      45,
      47,
      49,
      34,
      43,
      65,
      11,
      38,
      46,
      44,
      42,
      42,
      44,
      42,
      41,
      46,
      44,
      41,
      42,
      45,
      60,
      46,
      50,
      58,
      0,
      43,
      52,
      41,
      46,
      41,
      64,
      25,
      46,
      41,
      45,
      34,
      9,
      60,
      40,
      20,
      64,
      52,
      71,
      47,
      46,
      48,
      26,
      44
    ],
    [
      10,
      39,
      5,
      7,
      9,
      17,
      13,
      7,
      51,
      44,
      16,
      13,
      15,
      13,
      12,
      17,
      14,
      15,
      12,
      11,
      15,
      10,
      14,
      22,
      16,
      18,
      21,
      44,
      0,
      13,
      9,
      14,
      15,
      26,
      25,
      18,
      11,
      9,
      17,
      42,
      22,
      11,
      52,
      50,
      25,
      34,
      12,
      7,
      11,
      24,
      18
    ],
    [
      18,
      48,
      13,
      15,
      11,
      25,
      21,
      15,
      59,
      52,
      24,
      21,
      23,
      21,
      20,
      26,
      23,
      24,
      19,
      19,
      23,
      18,
      22,
      29,
      23,
      25,
      29,
      52,
      13,
      0,
      17,
      21,
      23,
      31,
      33,
      26,
      19,
      17,
      25,
      50,
      31,
      19,
      60,
      58,
      33,
      38,
      20,
      16,
      18,
      33,
      26
    ],
    [
      6,
      38,
      5,
      7,
      13,
      18,
      11,
      4,
      49,
      42,
      11,
      8,
      9,
      6,
      4,
      11,
      7,
      10,
      9,
      6,
      7,
      4,
      9,
      22,
      11,
      17,
      22,
      42,
      9,
      17,
      0,
      12,
      7,
      29,
      23,
      11,
      3,
      4,
      15,
      41,
      24,
      4,
      50,
      48,
      23,
      37,
      8,
      5,
      11,
      23,
      10
    ],
    [
      13,
      41,
      15,
      15,
      18,
      8,
      15,
      15,
      43,
      47,
      13,
      11,
      5,
      7,
      10,
      12,
      7,
      11,
      7,
      10,
      8,
      15,
      8,
      21,
      4,
      9,
      30,
      46,
      15,
      21,
      12,
      0,
      10,
      28,
      26,
      6,
      12,
      13,
      18,
      45,
      32,
      14,
      55,
      44,
      19,
      36,
      13,
      13,
      10,
      26,
      7
    ],
    [
      9,
      36,
      10,
      11,
      18,
      14,
      10,
      10,
      48,
      41,
      9,
      7,
      5,
      4,
      4,
      8,
      2,
      6,
      7,
      6,
      4,
      8,
      6,
      24,
      7,
      14,
      27,
      41,
      14,
      22,
      6,
      8,
      0,
      31,
      21,
      7,
      5,
      9,
      13,
      39,
      30,
      6,
      49,
      47,
      21,
      38,
      9,
      9,
      10,
      21,
      6
    ],
    [
      24,
      60,
      26,
      27,
      23,
      36,
      33,
      28,
      70,
      64,
      36,
      27,
      31,
      28,
      28,
      36,
      30,
      35,
      28,
      26,
      32,
      31,
      28,
      15,
      34,
      36,
      41,
      64,
      25,
      31,
      29,
      32,
      31,
      0,
      45,
      35,
      30,
      28,
      37,
      62,
      44,
      32,
      72,
      70,
      45,
      13,
      25,
      24,
      27,
      44,
      34
    ],
    [
      23,
      22,
      21,
      22,
      24,
      26,
      11,
      20,
      55,
      28,
      15,
      22,
      21,
      19,
      19,
      20,
      19,
      18,
      23,
      21,
      18,
      19,
      22,
      37,
      23,
      27,
      35,
      27,
      20,
      29,
      18,
      23,
      18,
      41,
      0,
      22,
      18,
      22,
      11,
      29,
      37,
      17,
      37,
      54,
      29,
      48,
      24,
      23,
      25,
      6,
      21
    ],
    [
      16,
      39,
      17,
      18,
      20,
      14,
      13,
      16,
      43,
      44,
      11,
      14,
      9,
      10,
      10,
      6,
      9,
      7,
      12,
      12,
      6,
      15,
      12,
      26,
      6,
      14,
      31,
      43,
      16,
      25,
      13,
      9,
      10,
      33,
      24,
      0,
      11,
      15,
      15,
      43,
      33,
      12,
      53,
      41,
      16,
      40,
      16,
      16,
      14,
      23,
      7
    ],
    [
      7,
      36,
      6,
      8,
      14,
      16,
      10,
      6,
      49,
      41,
      9,
      7,
      7,
      4,
      3,
      10,
      5,
      8,
      8,
      5,
      6,
      4,
      8,
      23,
      10,
      16,
      23,
      41,
      10,
      18,
      2,
      10,
      6,
      30,
      22,
      10,
      0,
      5,
      14,
      39,
      26,
      4,
      49,
      48,
      23,
      37,
      8,
      6,
      10,
      21,
      9
    ],
    [
      7,
      39,
      8,
      9,
      17,
      16,
      12,
      9,
      51,
      43,
      11,
      6,
      7,
      4,
      4,
      12,
      6,
      10,
      7,
      4,
      7,
      8,
      6,
      21,
      11,
      16,
      27,
      43,
      12,
      20,
      5,
      10,
      8,
      28,
      24,
      11,
      5,
      0,
      16,
      41,
      29,
      7,
      51,
      50,
      25,
      36,
      7,
      7,
      8,
      23,
      10
    ],
    [
      21,
      29,
      19,
      20,
      22,
      24,
      9,
      18,
      53,
      34,
      13,
      20,
      19,
      16,
      16,
      17,
      16,
      15,
      21,
      19,
      15,
      17,
      20,
      35,
      21,
      24,
      33,
      33,
      18,
      27,
      16,
      21,
      16,
      38,
      14,
      20,
      16,
      19,
      0,
      36,
      35,
      14,
      44,
      52,
      26,
      46,
      22,
      20,
      22,
      13,
      19
    ],
    [
      45,
      17,
      43,
      44,
      46,
      48,
      37,
      42,
      72,
      17,
      37,
      44,
      43,
      40,
      40,
      43,
      41,
      40,
      45,
      43,
      39,
      41,
      44,
      59,
      45,
      49,
      57,
      9,
      42,
      51,
      40,
      45,
      40,
      62,
      28,
      44,
      40,
      43,
      37,
      0,
      59,
      38,
      26,
      70,
      51,
      70,
      46,
      45,
      46,
      29,
      43
    ],
    [
      30,
      56,
      24,
      27,
      29,
      36,
      29,
      27,
      67,
      60,
      32,
      32,
      32,
      29,
      28,
      34,
      30,
      32,
      30,
      30,
      31,
      25,
      32,
      40,
      34,
      36,
      10,
      60,
      22,
      32,
      25,
      32,
      31,
      45,
      41,
      34,
      26,
      28,
      33,
      58,
      0,
      26,
      68,
      66,
      41,
      53,
      30,
      27,
      29,
      41,
      34
    ],
    [
      8,
      37,
      7,
      8,
      15,
      18,
      10,
      6,
      48,
      41,
      11,
      9,
      9,
      6,
      5,
      12,
      7,
      10,
      10,
      7,
      7,
      3,
      9,
      24,
      12,
      18,
      24,
      41,
      10,
      19,
      2,
      12,
      8,
      31,
      22,
      12,
      3,
      6,
      14,
      39,
      26,
      0,
      49,
      47,
      22,
      39,
      10,
      7,
      11,
      21,
      11
    ],
    [
      54,
      28,
      52,
      53,
      55,
      57,
      44,
      51,
      58,
      18,
      46,
      53,
      52,
      50,
      50,
      52,
      50,
      49,
      54,
      52,
      49,
      50,
      53,
      68,
      54,
      58,
      66,
      20,
      51,
      60,
      49,
      54,
      49,
      72,
      35,
      53,
      49,
      53,
      44,
      25,
      68,
      48,
      0,
      57,
      60,
      79,
      55,
      54,
      56,
      36,
      52
    ],
    [
      51,
      64,
      50,
      51,
      53,
      47,
      47,
      50,
      26,
      61,
      44,
      52,
      47,
      49,
      49,
      44,
      47,
      44,
      49,
      51,
      44,
      48,
      50,
      59,
      46,
      48,
      64,
      63,
      49,
      58,
      47,
      44,
      48,
      66,
      57,
      42,
      49,
      51,
      49,
      68,
      66,
      46,
      56,
      0,
      34,
      74,
      52,
      51,
      49,
      57,
      45
    ],
    [
      27,
      48,
      26,
      27,
      29,
      23,
      23,
      25,
      35,
      54,
      20,
      28,
      23,
      24,
      24,
      20,
      23,
      20,
      25,
      26,
      20,
      24,
      26,
      35,
      21,
      23,
      40,
      53,
      25,
      34,
      23,
      20,
      24,
      41,
      33,
      18,
      24,
      26,
      25,
      53,
      42,
      21,
      62,
      34,
      0,
      49,
      27,
      27,
      24,
      33,
      21
    ],
    [
      32,
      67,
      34,
      35,
      31,
      43,
      41,
      36,
      78,
      72,
      43,
      34,
      38,
      36,
      36,
      44,
      38,
      42,
      35,
      34,
      40,
      39,
      36,
      22,
      41,
      43,
      49,
      72,
      33,
      38,
      37,
      40,
      39,
      12,
      52,
      42,
      38,
      35,
      45,
      70,
      51,
      39,
      80,
      78,
      52,
      0,
      32,
      32,
      34,
      52,
      41
    ],
    [
      3,
      41,
      8,
      7,
      16,
      15,
      15,
      8,
      49,
      46,
      14,
      5,
      9,
      6,
      6,
      14,
      8,
      13,
      6,
      4,
      10,
      10,
      6,
      16,
      13,
      15,
      27,
      46,
      11,
      19,
      7,
      11,
      10,
      23,
      27,
      13,
      8,
      6,
      19,
      44,
      30,
      10,
      54,
      50,
      25,
      31,
      0,
      4,
      6,
      26,
      12
    ],
    [
      4,
      42,
      5,
      4,
      13,
      15,
      16,
      6,
      50,
      47,
      15,
      6,
      10,
      7,
      7,
      15,
      9,
      13,
      7,
      5,
      11,
      8,
      8,
      17,
      13,
      16,
      25,
      47,
      8,
      16,
      6,
      12,
      11,
      24,
      27,
      14,
      7,
      6,
      19,
      45,
      27,
      9,
      55,
      51,
      25,
      32,
      5,
      0,
      6,
      27,
      13
    ],
    [
      7,
      43,
      11,
      10,
      15,
      14,
      17,
      12,
      48,
      48,
      16,
      5,
      7,
      8,
      7,
      15,
      8,
      14,
      4,
      6,
      11,
      12,
      5,
      18,
      11,
      14,
      27,
      48,
      12,
      18,
      10,
      10,
      11,
      25,
      29,
      13,
      10,
      9,
      21,
      46,
      29,
      12,
      56,
      49,
      24,
      33,
      8,
      7,
      0,
      28,
      12
    ],
    [
      26,
      22,
      24,
      25,
      27,
      29,
      14,
      23,
      58,
      27,
      18,
      26,
      24,
      22,
      22,
      24,
      22,
      21,
      26,
      24,
      21,
      22,
      25,
      40,
      26,
      30,
      38,
      26,
      23,
      32,
      21,
      26,
      22,
      44,
      5,
      26,
      21,
      25,
      14,
      29,
      40,
      20,
      37,
      57,
      32,
      51,
      27,
      26,
      28,
      0,
      24
    ],
    [
      13,
      39,
      15,
      15,
      21,
      12,
      13,
      15,
      46,
      45,
      12,
      11,
      7,
      7,
      8,
      6,
      6,
      8,
      9,
      10,
      5,
      13,
      9,
      25,
      5,
      12,
      32,
      43,
      17,
      25,
      11,
      7,
      8,
      32,
      24,
      5,
      10,
      13,
      16,
      43,
      34,
      12,
      53,
      45,
      20,
      39,
      13,
      13,
      12,
      24,
      0
    ]
  ],
  "terminal_points": [
    {
      "id": "d0",
      "distance_matrix_index": 0,
      "location": [
        -0.8691257441383268,
        41.64395569318226
      ]
    }
  ],
  "caregivers": [
    {
      "id": "c1",
      "abilities": [
        "s3"
      ],
      "departing_point": "d0",
      "arrival_point": "d0",
      "working_shift": {
        "start": 0,
        "end": 600
      },
      "lunch_break": true
    },
    {
      "id": "c2",
      "abilities": [
        "s4"
      ],
      "departing_point": "d0",
      "arrival_point": "d0",
      "working_shift": {
        "start": 30,
        "end": 630
      },
      "lunch_break": true
    },
    {
      "id": "c3",
      "abilities": [
        "s1",
        "s0"
      ],
      "departing_point": "d0",
      "arrival_point": "d0",
      "working_shift": {
        "start": 0,
        "end": 600
      },
      "lunch_break": true
    },
    {
      "id": "c4",
      "abilities": [
        "s5",
        "s4"
      ],
      "departing_point": "d0",
      "arrival_point": "d0",
      "working_shift": {
        "start": 0,
        "end": 600
      },
      "lunch_break": true
    },
    {
      "id": "c5",
      "abilities": [
        "s2",
        "s0"
      ],
      "departing_point": "d0",
      "arrival_point": "d0",
      "working_shift": {
        "start": 30,
        "end": 630
      },
      "lunch_break": true
    }
  ],
  "patients": [
    {
      "id": "p0",
      "required_services": [
        {
          "service": "s0",
          "duration": 15
        }
      ],
      "distance_matrix_index": 1,
      "time_windows": [
        {
          "start": 0,
          "end": 240
        },
        {
          "start": 300,
          "end": 540
        }
      ],
      "location": [
        -1.2424018388041507,
        41.83020865147919
      ],
      "optional": false
    },
    {
      "id": "p1",
      "required_services": [
        {
          "service": "s1",
          "duration": 15
        }
      ],
      "distance_matrix_index": 2,
      "time_windows": [
        {
          "start": 15,
          "end": 255
        },
        {
          "start": 270,
          "end": 510
        }
      ],
      "location": [
        -0.8604404079741665,
        41.66311827464311
      ],
      "optional": false
    },
    {
      "id": "p2",
      "required_services": [
        {
          "service": "s1",
          "duration": 15
        }
      ],
      "distance_matrix_index": 3,
      "time_windows": [
        {
          "start": 75,
          "end": 315
        },
        {
          "start": 345,
          "end": 585
        }
      ],
      "location": [
        -0.8588491124426181,
        41.654185358034844
      ],
      "optional": false
    },
    {
      "id": "p3",
      "required_services": [
        {
          "service": "s1",
          "duration": 35
        }
      ],
      "distance_matrix_index": 4,
      "time_windows": [
        {
          "start": 15,
          "end": 255
        },
        {
          "start": 255,
          "end": 495
        }
      ],
      "location": [
        -0.7591515156736898,
        41.637704845517874
      ],
      "optional": false
    },
    {
      "id": "p4",
      "required_services": [
        {
          "service": "s0",
          "duration": 35
        }
      ],
      "distance_matrix_index": 5,
      "time_windows": [
        {
          "start": 60,
          "end": 300
        },
        {
          "start": 330,
          "end": 570
        }
      ],
      "location": [
        -0.9970154233144187,
        41.54790965806107
      ],
      "optional": false
    },
    {
      "id": "p5",
      "required_services": [
        {
          "service": "s0",
          "duration": 35
        }
      ],
      "distance_matrix_index": 6,
      "time_windows": [
        {
          "start": 45,
          "end": 285
        },
        {
          "start": 285,
          "end": 525
        }
      ],
      "location": [
        -0.9634261506154405,
        41.69735635999972
      ],
      "optional": false
    },
    {
      "id": "p6",
      "required_services": [
        {
          "service": "s4",
          "duration": 15
        }
      ],
      "distance_matrix_index": 7,
      "time_windows": [
        {
          "start": 0,
          "end": 240
        },
        {
          "start": 345,
          "end": 585
        }
      ],
      "location": [
        -0.8723110582674269,
        41.661821203267344
      ],
      "optional": false
    },
    {
      "id": "p7",
      "required_services": [
        {
          "service": "s1",
          "duration": 35
        }
      ],
      "distance_matrix_index": 8,
      "time_windows": [
        {
          "start": 15,
          "end": 255
        }
      ],
      "location": [
        -1.3205726119532732,
        41.40215956304978
      ],
      "optional": false
    },
    {
      "id": "p8",
      "required_services": [
        {
          "service": "s2",
          "duration": 35
        }
      ],
      "distance_matrix_index": 9,
      "time_windows": [
        {
          "start": 30,
          "end": 270
        },
        {
          "start": 315,
          "end": 555
        }
      ],
      "location": [
        -1.413818029675373,
        41.90184041166001
      ],
      "optional": false
    },
    {
      "id": "p9",
      "required_services": [
        {
          "service": "s5",
          "duration": 35
        }
      ],
      "distance_matrix_index": 10,
      "time_windows": [
        {
          "start": 90,
          "end": 330
        },
        {
          "start": 330,
          "end": 570
        }
      ],
      "location": [
        -0.8754988879971625,
        41.67968625319969
      ],
      "optional": false
    },
    {
      "id": "p10",
      "required_services": [
        {
          "service": "s4",
          "duration": 35
        }
      ],
      "distance_matrix_index": 11,
      "time_windows": [
        {
          "start": 270,
          "end": 510
        }
      ],
      "location": [
        -0.8793992117654352,
        41.63372494463975
      ],
      "optional": false
    },
    {
      "id": "p11",
      "required_services": [
        {
          "service": "s2",
          "duration": 15
        }
      ],
      "distance_matrix_index": 12,
      "time_windows": [
        {
          "start": 45,
          "end": 285
        },
        {
          "start": 330,
          "end": 570
        }
      ],
      "location": [
        -0.9031282466900612,
        41.63112508369942
      ],
      "optional": false
    },
    {
      "id": "p12",
      "required_services": [
        {
          "service": "s1",
          "duration": 35
        }
      ],
      "distance_matrix_index": 13,
      "time_windows": [
        {
          "start": 15,
          "end": 255
        }
      ],
      "location": [
        -0.8928590138021409,
        41.64135820650728
      ],
      "optional": false
    },
    {
      "id": "p13",
      "required_services": [
        {
          "service": "s3",
          "duration": 15
        }
      ],
      "distance_matrix_index": 14,
      "time_windows": [
        {
          "start": 330,
          "end": 570
        }
      ],
      "location": [
        -0.8944547061441382,
        41.65029058038403
      ],
      "optional": false
    },
    {
      "id": "p14",
      "required_services": [
        {
          "service": "s4",
          "duration": 35
        }
      ],
      "distance_matrix_index": 15,
      "time_windows": [
        {
          "start": 270,
          "end": 510
        }
      ],
      "location": [
        -0.9419226133169756,
        41.64507784866669
      ],
      "optional": false
    },
    {
      "id": "p15",
      "required_services": [
        {
          "service": "s5",
          "duration": 35
        }
      ],
      "distance_matrix_index": 16,
      "time_windows": [
        {
          "start": 120,
          "end": 360
        }
      ],
      "location": [
        -0.9047249832882932,
        41.640057353260985
      ],
      "optional": false
    },
    {
      "id": "p16",
      "required_services": [
        {
          "service": "s4",
          "duration": 15
        }
      ],
      "distance_matrix_index": 17,
      "time_windows": [
        {
          "start": 105,
          "end": 345
        },
        {
          "start": 345,
          "end": 585
        }
      ],
      "location": [
        -0.9316576504184795,
        41.65531474012277
      ],
      "optional": false
    },
    {
      "id": "p17",
      "required_services": [
        {
          "service": "s0",
          "duration": 15
        }
      ],
      "distance_matrix_index": 18,
      "time_windows": [
        {
          "start": 270,
          "end": 510
        }
      ],
      "location": [
        -0.8896695172461776,
        41.62349311286595
      ],
      "optional": false
    },
    {
      "id": "p18",
      "required_services": [
        {
          "service": "s0",
          "duration": 15
        }
      ],
      "distance_matrix_index": 19,
      "time_windows": [
        {
          "start": 195,
          "end": 435
        }
      ],
      "location": [
        -0.8809926006054452,
        41.64265765317569
      ],
      "optional": false
    },
    {
      "id": "p19",
      "required_services": [
        {
          "service": "s3",
          "duration": 15
        }
      ],
      "distance_matrix_index": 20,
      "time_windows": [
        {
          "start": 75,
          "end": 315
        },
        {
          "start": 330,
          "end": 570
        }
      ],
      "location": [
        -0.9181895494496377,
        41.64768702779484
      ],
      "optional": false
    },
    {
      "id": "p20",
      "required_services": [
        {
          "service": "s4",
          "duration": 35
        }
      ],
      "distance_matrix_index": 21,
      "time_windows": [
        {
          "start": 300,
          "end": 540
        }
      ],
      "location": [
        -0.8857765416180761,
        41.66945508774694
      ],
      "optional": false
    },
    {
      "id": "p21",
      "required_services": [
        {
          "service": "s5",
          "duration": 15
        }
      ],
      "distance_matrix_index": 22,
      "time_windows": [
        {
          "start": 90,
          "end": 330
        }
      ],
      "location": [
        -0.8912639509487561,
        41.63242571734598
      ],
      "optional": false
    },
    {
      "id": "p22",
      "required_services": [
        {
          "service": "s3",
          "duration": 15
        }
      ],
      "distance_matrix_index": 23,
      "time_windows": [
        {
          "start": 45,
          "end": 285
        },
        {
          "start": 345,
          "end": 585
        }
      ],
      "location": [
        -0.7212892111799288,
        41.55984642661765
      ],
      "optional": false
    },
    {
      "id": "p23",
      "required_services": [
        {
          "service": "s2",
          "duration": 35
        }
      ],
      "distance_matrix_index": 24,
      "time_windows": [
        {
          "start": 75,
          "end": 315
        },
        {
          "start": 315,
          "end": 555
        }
      ],
      "location": [
        -0.9268555060878949,
        41.628519597684225
      ],
      "optional": false
    },
    {
      "id": "p24",
      "required_services": [
        {
          "service": "s5",
          "duration": 35
        }
      ],
      "distance_matrix_index": 25,
      "time_windows": [
        {
          "start": 105,
          "end": 345
        },
        {
          "start": 345,
          "end": 585
        }
      ],
      "location": [
        -0.963074991158215,
        41.56077187413176
      ],
      "optional": false
    },
    {
      "id": "p25",
      "required_services": [
        {
          "service": "s5",
          "duration": 35
        }
      ],
      "distance_matrix_index": 26,
      "time_windows": [
        {
          "start": 45,
          "end": 285
        },
        {
          "start": 300,
          "end": 540
        }
      ],
      "location": [
        -0.7884192060654625,
        41.87126708416363
      ],
      "optional": false
    },
    {
      "id": "p26",
      "required_services": [
        {
          "service": "s1",
          "duration": 15
        }
      ],
      "distance_matrix_index": 27,
      "time_windows": [
        {
          "start": 0,
          "end": 240
        }
      ],
      "location": [
        -1.3102035947290365,
        41.868090667685834
      ],
      "optional": false
    },
    {
      "id": "p27",
      "required_services": [
        {
          "service": "s0",
          "duration": 35
        }
      ],
      "distance_matrix_index": 28,
      "time_windows": [
        {
          "start": 345,
          "end": 585
        }
      ],
      "location": [
        -0.8264126941527319,
        41.67593450263069
      ],
      "optional": false
    },
    {
      "id": "p28",
      "required_services": [
        {
          "service": "s0",
          "duration": 35
        }
      ],
      "distance_matrix_index": 29,
      "time_windows": [
        {
          "start": 30,
          "end": 270
        },
        {
          "start": 285,
          "end": 525
        }
      ],
      "location": [
        -0.7915924115548764,
        41.61597674943348
      ],
      "optional": false
    },
    {
      "id": "p29",
      "required_services": [
        {
          "service": "s4",
          "duration": 35
        }
      ],
      "distance_matrix_index": 30,
      "time_windows": [
        {
          "start": 45,
          "end": 285
        },
        {
          "start": 315,
          "end": 555
        }
      ],
      "location": [
        -0.8841812651939059,
        41.660522724695085
      ],
      "optional": false
    },
    {
      "id": "p30",
      "required_services": [
        {
          "service": "s3",
          "duration": 15
        }
      ],
      "distance_matrix_index": 31,
      "time_windows": [
        {
          "start": 15,
          "end": 255
        },
        {
          "start": 315,
          "end": 555
        }
      ],
      "location": [
        -0.925256053850408,
        41.61958765241123
      ],
      "optional": false
    },
    {
      "id": "p31",
      "required_services": [
        {
          "service": "s4",
          "duration": 15
        }
      ],
      "distance_matrix_index": 32,
      "time_windows": [
        {
          "start": 210,
          "end": 450
        }
      ],
      "location": [
        -0.9063223500066427,
        41.64898950744892
      ],
      "optional": false
    },
    {
      "id": "p32",
      "required_services": [
        {
          "service": "s0",
          "duration": 35
        }
      ],
      "distance_matrix_index": 33,
      "time_windows": [
        {
          "start": 75,
          "end": 315
        }
      ],
      "location": [
        -0.6289846063175888,
        41.51513813657246
      ],
      "optional": false
    },
    {
      "id": "p33",
      "required_services": [
        {
          "service": "s4",
          "duration": 15
        }
      ],
      "distance_matrix_index": 34,
      "time_windows": [
        {
          "start": 45,
          "end": 285
        }
      ],
      "location": [
        -1.0800403397534213,
        41.739089833831294
      ],
      "optional": false
    },
    {
      "id": "p34",
      "required_services": [
        {
          "service": "s5",
          "duration": 35
        }
      ],
      "distance_matrix_index": 35,
      "time_windows": [
        {
          "start": 135,
          "end": 375
        }
      ],
      "location": [
        -0.9403202250844618,
        41.63614635489598
      ],
      "optional": false
    },
    {
      "id": "p35",
      "required_services": [
        {
          "service": "s3",
          "duration": 35
        }
      ],
      "distance_matrix_index": 36,
      "time_windows": [
        {
          "start": 225,
          "end": 465
        }
      ],
      "location": [
        -0.8960510283127919,
        41.65922283901038
      ],
      "optional": false
    },
    {
      "id": "p36",
      "required_services": [
        {
          "service": "s1",
          "duration": 35
        }
      ],
      "distance_matrix_index": 37,
      "time_windows": [
        {
          "start": 0,
          "end": 240
        },
        {
          "start": 255,
          "end": 495
        }
      ],
      "location": [
        -0.8825866183023504,
        41.65159024651607
      ],
      "optional": false
    },
    {
      "id": "p37",
      "required_services": [
        {
          "service": "s4",
          "duration": 35
        }
      ],
      "distance_matrix_index": 38,
      "time_windows": [
        {
          "start": 0,
          "end": 240
        },
        {
          "start": 345,
          "end": 585
        }
      ],
      "location": [
        -1.002278911311973,
        41.71128332206949
      ],
      "optional": false
    },
    {
      "id": "p38",
      "required_services": [
        {
          "service": "s0",
          "duration": 15
        }
      ],
      "distance_matrix_index": 39,
      "time_windows": [
        {
          "start": 30,
          "end": 270
        },
        {
          "start": 315,
          "end": 555
        }
      ],
      "location": [
        -1.2589853262896753,
        41.919439988708255
      ],
      "optional": false
    },
    {
      "id": "p39",
      "required_services": [
        {
          "service": "s4",
          "duration": 15
        }
      ],
      "distance_matrix_index": 40,
      "time_windows": [
        {
          "start": 30,
          "end": 270
        },
        {
          "start": 345,
          "end": 585
        }
      ],
      "location": [
        -0.758251875614327,
        41.838109317536656
      ],
      "optional": false
    },
    {
      "id": "p40",
      "required_services": [
        {
          "service": "s4",
          "duration": 15
        }
      ],
      "distance_matrix_index": 41,
      "time_windows": [
        {
          "start": 345,
          "end": 585
        }
      ],
      "location": [
        -0.8976479806464256,
        41.66815498242044
      ],
      "optional": false
    },
    {
      "id": "p41",
      "required_services": [
        {
          "service": "s2",
          "duration": 15
        }
      ],
      "distance_matrix_index": 42,
      "time_windows": [
        {
          "start": 240,
          "end": 480
        }
      ],
      "location": [
        -1.5345677814473144,
        41.83325805447308
      ],
      "optional": false
    },
    {
      "id": "p42",
      "required_services": [
        {
          "service": "s3",
          "duration": 35
        }
      ],
      "distance_matrix_index": 43,
      "time_windows": [
        {
          "start": 345,
          "end": 585
        }
      ],
      "location": [
        -1.4790035115970765,
        41.47508553928931
      ],
      "optional": false
    },
    {
      "id": "p43",
      "required_services": [
        {
          "service": "s5",
          "duration": 15
        }
      ],
      "distance_matrix_index": 44,
      "time_windows": [
        {
          "start": 285,
          "end": 525
        }
      ],
      "location": [
        -1.1015046254107321,
        41.590941866676296
      ],
      "optional": false
    },
    {
      "id": "p44",
      "required_services": [
        {
          "service": "s2",
          "duration": 35
        }
      ],
      "distance_matrix_index": 45,
      "time_windows": [
        {
          "start": 300,
          "end": 540
        }
      ],
      "location": [
        -0.5280514038189548,
        41.489477500252136
      ],
      "optional": false
    },
    {
      "id": "p45",
      "required_services": [
        {
          "service": "s5",
          "duration": 15
        }
      ],
      "distance_matrix_index": 46,
      "time_windows": [
        {
          "start": 345,
          "end": 585
        }
      ],
      "location": [
        -0.8675340295799785,
        41.635022765496885
      ],
      "optional": false
    },
    {
      "id": "p46",
      "required_services": [
        {
          "service": "s5",
          "duration": 35
        }
      ],
      "distance_matrix_index": 47,
      "time_windows": [
        {
          "start": 60,
          "end": 300
        },
        {
          "start": 345,
          "end": 585
        }
      ],
      "location": [
        -0.8572584448410678,
        41.645252326443064
      ],
      "optional": false
    },
    {
      "id": "p47",
      "required_services": [
        {
          "service": "s0",
          "duration": 35
        }
      ],
      "distance_matrix_index": 48,
      "time_windows": [
        {
          "start": 135,
          "end": 375
        }
      ],
      "location": [
        -0.8778064514448412,
        41.62479212087412
      ],
      "optional": false
    },
    {
      "id": "p48",
      "required_services": [
        {
          "service": "s2",
          "duration": 35
        }
      ],
      "distance_matrix_index": 49,
      "time_windows": [
        {
          "start": 285,
          "end": 525
        }
      ],
      "location": [
        -1.0919218179632517,
        41.737766393428906
      ],
      "optional": false
    },
    {
      "id": "p49",
      "required_services": [
        {
          "service": "s0",
          "duration": 35
        }
      ],
      "distance_matrix_index": 50,
      "time_windows": [
        {
          "start": 0,
          "end": 240
        },
        {
          "start": 300,
          "end": 540
        }
      ],
      "location": [
        -0.9284555893691917,
        41.63745142737115
      ],
      "optional": false
    }
  ],
  "services": [
    {
      "id": "s0",
      "type": "t0",
      "default_duration": 35
    },
    {
      "id": "s1",
      "type": "t0",
      "default_duration": 35
    },
    {
      "id": "s2",
      "type": "t0",
      "default_duration": 35
    },
    {
      "id": "s3",
      "type": "t1",
      "default_duration": 15
    },
    {
      "id": "s4",
      "type": "t1",
      "default_duration": 15
    },
    {
      "id": "s5",
      "type": "t1",
      "default_duration": 35
    }
  ],
  "lunch_breaks": {
    "start": 180,
    "end": 360,
    "min_duration": 30
  }
}